graceful_checker/__init__.py
graceful_checker-0.1.2.dist-info/DESCRIPTION.rst
graceful_checker-0.1.2.dist-info/METADATA
graceful_checker-0.1.2.dist-info/RECORD
graceful_checker-0.1.2.dist-info/WHEEL
graceful_checker-0.1.2.dist-info/metadata.json
graceful_checker-0.1.2.dist-info/top_level.txt
