Metadata-Version: 2.0
Name: graceful-checker
Version: 0.1.2
Summary: Easily create a graceful linter.
Home-page: https://github.com/kalibrr/graceful-checker
Author: Tim Dumol, Kalibrr Technology Ventures, Inc.
Author-email: tim@kalibrr.com
License: mit
Platform: UNKNOWN
Classifier: Development Status :: 4 - Beta
Classifier: Programming Language :: Python
Requires-Dist: six (>=1.11.0)
